JupyterJournal/__init__.py
JupyterJournal/_modidx.py
JupyterJournal/core.py
JupyterJournal-0.0.1.dist-info/LICENSE
JupyterJournal-0.0.1.dist-info/METADATA
JupyterJournal-0.0.1.dist-info/WHEEL
JupyterJournal-0.0.1.dist-info/entry_points.txt
JupyterJournal-0.0.1.dist-info/top_level.txt
JupyterJournal-0.0.1.dist-info/RECORD
