Metadata-Version: 2.1
Name: JupyterJournal
Version: 0.0.1
Summary: Effortlessly transform Jupyter notebooks into beautiful blog posts with auto-generated HTML.
Home-page: https://github.com/audreyfeldroy/JupyterJournal
Author: Audrey M. Roy Greenfeld
Author-email: arg@answer.ai
License: Apache Software License 2.0
Keywords: nbdev jupyter notebook python
Classifier: Development Status :: 4 - Beta
Classifier: Intended Audience :: Developers
Classifier: Natural Language :: English
Classifier: Programming Language :: Python :: 3.7
Classifier: Programming Language :: Python :: 3.8
Classifier: Programming Language :: Python :: 3.9
Classifier: Programming Language :: Python :: 3.10
Classifier: Programming Language :: Python :: 3.11
Classifier: Programming Language :: Python :: 3.12
Classifier: License :: OSI Approved :: Apache Software License
Requires-Python: >=3.7
License-File: LICENSE
Provides-Extra: dev
